sentry_auth_authsch/__init__.py
sentry_auth_authsch/apps.py
sentry_auth_authsch/constants.py
sentry_auth_authsch/provider.py
sentry_auth_authsch/views.py
sentry_auth_authsch/templates/sentry_auth_authsch/configure.html
sentry_auth_authsch-1.0.1.dist-info/METADATA
sentry_auth_authsch-1.0.1.dist-info/WHEEL
sentry_auth_authsch-1.0.1.dist-info/entry_points.txt
sentry_auth_authsch-1.0.1.dist-info/top_level.txt
sentry_auth_authsch-1.0.1.dist-info/RECORD
