Metadata-Version: 2.1
Name: sentry-auth-authsch
Version: 1.0.1
Summary: AuthSCH SSO integration for Sentry
Home-page: https://github.com/thomasklein94/sentry-auth-authsch.git
Author: Tamas Kiss
Author-email: tamas.kiss@kszk.bme.hu
License: Simplified BSD
Platform: UNKNOWN
Classifier: Framework :: Django
Classifier: Intended Audience :: Developers
Classifier: Intended Audience :: System Administrators
Classifier: Operating System :: OS Independent
Classifier: Topic :: Software Development
Requires-Dist: requests (<3.0.0,>=2.20)
Provides-Extra: tests
Requires-Dist: exam ; extra == 'tests'
Requires-Dist: responses ; extra == 'tests'
Requires-Dist: flake8 (<2.1,>=2.0) ; extra == 'tests'
Requires-Dist: pytest (<3.6.0,>=3.5.0) ; extra == 'tests'
Requires-Dist: betamax (==0.8.1) ; extra == 'tests'
Requires-Dist: sentry (<10.0.0,>=9.1.0) ; extra == 'tests'
